AUTHORS.rst
CONTRIBUTING.rst
HISTORY.rst
LICENSE
MANIFEST.in
README.rst
setup.cfg
setup.py
docs/Makefile
docs/authors.rst
docs/conf.py
docs/contributing.rst
docs/history.rst
docs/index.rst
docs/installation.rst
docs/make.bat
docs/modules.rst
docs/readme.rst
docs/send_words.rst
docs/usage.rst
docs/_build/html/_static/ajax-loader.gif
docs/_build/html/_static/comment-bright.png
docs/_build/html/_static/comment-close.png
docs/_build/html/_static/comment.png
docs/_build/html/_static/down-pressed.png
docs/_build/html/_static/down.png
docs/_build/html/_static/file.png
docs/_build/html/_static/minus.png
docs/_build/html/_static/plus.png
docs/_build/html/_static/up-pressed.png
docs/_build/html/_static/up.png
send_words/__init__.py
send_words/cli.py
send_words/send_words.py
send_words.egg-info/PKG-INFO
send_words.egg-info/SOURCES.txt
send_words.egg-info/dependency_links.txt
send_words.egg-info/entry_points.txt
send_words.egg-info/not-zip-safe
send_words.egg-info/requires.txt
send_words.egg-info/top_level.txt
tests/test_send_words.py