Metadata-Version: 1.1
Name: send-words
Version: 0.1.0
Summary: Package that send a word or words set to service and get the syllabes of each phrase sent
Home-page: https://github.com/bgarcial/send_words
Author: Bernardo Augusto Garcia Loaiza
Author-email: botibagl@gmail.com
License: MIT license
Keywords: send_words
Platform: UNKNOWN
Classifier: Development Status :: 2 - Pre-Alpha
Classifier: Intended Audience :: Developers
Classifier: License :: OSI Approved :: MIT License
Classifier: Natural Language :: English
Classifier: Programming Language :: Python :: 3.6
